libro/config.py
libro/main.py
libro/models.py
libro/py.typed
libro/actions/db.py
libro/actions/importer.py
libro/actions/lists.py
libro/actions/modify.py
libro/actions/report.py
libro/actions/show.py
libro/tui/__init__.py
libro/tui/app.py
libro/tui/screens/__init__.py
libro/tui/screens/add_book.py
libro/tui/screens/book_detail.py
libro/tui/screens/edit_book.py
libro/tui/screens/reading_list.py
libro/tui/screens/reading_lists.py
libro/tui/screens/year_select.py
libro_book-0.6.1.dist-info/METADATA
libro_book-0.6.1.dist-info/WHEEL
libro_book-0.6.1.dist-info/entry_points.txt
libro_book-0.6.1.dist-info/licenses/LICENSE
libro_book-0.6.1.dist-info/RECORD
