Metadata-Version: 2.4
Name: libro-book
Version: 0.6.1
Summary: A command-line tool to track books read
Project-URL: Documentation, https://github.com/mkaz/libro
Project-URL: Repository, https://github.com/mkaz/libro
Project-URL: Issues, https://github.com/mkaz/libro/issues
Author-email: Marcus Kazmierczak <marcus@mkaz.com>
License-Expression: MIT
License-File: LICENSE
Keywords: books,library,reading
Classifier: Development Status :: 4 - Beta
Classifier: Environment :: Console
Classifier: Intended Audience :: End Users/Desktop
Classifier: Natural Language :: English
Classifier: Operating System :: OS Independent
Classifier: Programming Language :: Python :: 3
Requires-Python: >=3.10
Requires-Dist: appdirs>=1.4
Requires-Dist: prompt-toolkit
Requires-Dist: rich>=13.3
Requires-Dist: textual>=5.3.0
